odoo8_addon_document_ocr-8.0.1.0.0-py2.7-nspkg.pth
odoo_addons/document_ocr/__openerp__.py
odoo_addons/document_ocr/__init__.py
odoo_addons/document_ocr/README.rst
odoo_addons/document_ocr/models/__init__.py
odoo_addons/document_ocr/models/ir_attachment.py
odoo_addons/document_ocr/data/ir_config_parameter.xml
odoo_addons/document_ocr/data/ir_cron.xml
odoo_addons/document_ocr/tests/test_document_ocr.py
odoo_addons/document_ocr/tests/__init__.py
odoo_addons/document_ocr/static/description/icon.png
odoo8_addon_document_ocr-8.0.1.0.0.dist-info/top_level.txt
odoo8_addon_document_ocr-8.0.1.0.0.dist-info/WHEEL
odoo8_addon_document_ocr-8.0.1.0.0.dist-info/RECORD
odoo8_addon_document_ocr-8.0.1.0.0.dist-info/metadata.json
odoo8_addon_document_ocr-8.0.1.0.0.dist-info/DESCRIPTION.rst
odoo8_addon_document_ocr-8.0.1.0.0.dist-info/METADATA
odoo8_addon_document_ocr-8.0.1.0.0.dist-info/namespace_packages.txt
